py.typed
codat_sync_for_expenses/__init__.py
codat_sync_for_expenses/_hooks/__init__.py
codat_sync_for_expenses/_hooks/registration.py
codat_sync_for_expenses/_hooks/sdkhooks.py
codat_sync_for_expenses/_hooks/types.py
codat_sync_for_expenses/_version.py
codat_sync_for_expenses/accounts.py
codat_sync_for_expenses/adjustments.py
codat_sync_for_expenses/attachments.py
codat_sync_for_expenses/bank_accounts.py
codat_sync_for_expenses/basesdk.py
codat_sync_for_expenses/companies.py
codat_sync_for_expenses/company_info.py
codat_sync_for_expenses/configuration.py
codat_sync_for_expenses/connections.py
codat_sync_for_expenses/customers.py
codat_sync_for_expenses/expenses.py
codat_sync_for_expenses/httpclient.py
codat_sync_for_expenses/manage_data.py
codat_sync_for_expenses/mapping_options.py
codat_sync_for_expenses/models/errors/__init__.py
codat_sync_for_expenses/models/errors/errormessage.py
codat_sync_for_expenses/models/errors/sdkerror.py
codat_sync_for_expenses/models/operations/__init__.py
codat_sync_for_expenses/models/operations/create_account.py
codat_sync_for_expenses/models/operations/create_adjustment_transaction.py
codat_sync_for_expenses/models/operations/create_bank_account.py
codat_sync_for_expenses/models/operations/create_connection.py
codat_sync_for_expenses/models/operations/create_customer.py
codat_sync_for_expenses/models/operations/create_expense_transaction.py
codat_sync_for_expenses/models/operations/create_partner_expense_connection.py
codat_sync_for_expenses/models/operations/create_reimbursable_expense_transaction.py
codat_sync_for_expenses/models/operations/create_supplier.py
codat_sync_for_expenses/models/operations/create_transfer_transaction.py
codat_sync_for_expenses/models/operations/delete_company.py
codat_sync_for_expenses/models/operations/delete_connection.py
codat_sync_for_expenses/models/operations/get_company.py
codat_sync_for_expenses/models/operations/get_company_configuration.py
codat_sync_for_expenses-7.0.1.dist-info/METADATA
codat_sync_for_expenses-7.0.1.dist-info/WHEEL
codat_sync_for_expenses-7.0.1.dist-info/RECORD
